README
setup.py
beaker/__init__.py
beaker/ext/__init__.py
beaker/ext/mongodb.py
beaker_mongo.egg-info/PKG-INFO
beaker_mongo.egg-info/SOURCES.txt
beaker_mongo.egg-info/dependency_links.txt
beaker_mongo.egg-info/entry_points.txt
beaker_mongo.egg-info/requires.txt
beaker_mongo.egg-info/top_level.txt
beaker_mongo.egg-info/zip-safe