Metadata-Version: 1.1
Name: beaker-mongo
Version: 0.2.2
Summary: Beaker backend MongoDB
Home-page: http://bitbucket.org/cent/beaker-mongo/
Author: Vadim Statishin
Author-email: statishin@gmail.com
License: New BSD License
Keywords: mongo mongodb beaker cache session
Platform: UNKNOWN
Classifier: Development Status :: 4 - Beta
Classifier: Environment :: Other Environment
Classifier: Environment :: Web Environment
Classifier: Intended Audience :: Developers
Classifier: License :: OSI Approved :: BSD License
Classifier: Operating System :: OS Independent
Classifier: Programming Language :: Python
Classifier: Topic :: Database
Classifier: Topic :: Utilities
Classifier: Topic :: Software Development :: Libraries :: Python Modules
Requires: pymongo
Requires: beaker
